AUTHORS.rst
CONTRIBUTING.rst
HISTORY.rst
LICENSE
MANIFEST.in
README.rst
setup.cfg
setup.py
demo/__init__.py
demo/aned.py
demo/cli.py
demo/demo.py
demo/parser.py
demo/wsd.py
demo/arabiner/__init__.py
demo/arabiner/bin/__init__.py
demo/arabiner/bin/infer.py
demo/arabiner/utils/__init__.py
demo/arabiner/utils/data.py
demo/arabiner/utils/helpers.py
demo/jaccard/__init__.py
demo/jaccard/jaccardFunction.py
demo/morph/__init__.py
demo/morph/charsets.py
demo/morph/lemmatizeSentence.py
demo/morph/morph_tagger.py
demo/morph/serializers.py
demo/morph/settings.py
demo/morph/tokenizers_words.py
demo/salma/__init__.py
demo/salma/implication.py
demo/salma/tokenizers_words.py
demo/salma/views.py
demo/salma/wsd.py
demo_abc.egg-info/PKG-INFO
demo_abc.egg-info/SOURCES.txt
demo_abc.egg-info/dependency_links.txt
demo_abc.egg-info/entry_points.txt
demo_abc.egg-info/not-zip-safe
demo_abc.egg-info/top_level.txt
docs/Makefile
docs/authors.rst
docs/conf.py
docs/contributing.rst
docs/history.rst
docs/index.rst
docs/installation.rst
docs/make.bat
docs/readme.rst
docs/usage.rst
tests/__init__.py
tests/test_demo.py